officeextractor/__init__.py
officeextractor/exceptions.py
officeextractor/main.py
officeextractor-0.1.2.dist-info/LICENSE
officeextractor-0.1.2.dist-info/METADATA
officeextractor-0.1.2.dist-info/WHEEL
officeextractor-0.1.2.dist-info/top_level.txt
officeextractor-0.1.2.dist-info/RECORD
