Metadata-Version: 2.1
Name: officeextractor
Version: 0.1.2
Summary: officeextractor extracts media files (images, videos, music) from Microsoft Office and LibreOffice files.
Home-page: https://github.com/fbernhart/officeextractor
Author: Florian Bernhart
Author-email: florian-bernhart@hotmail.com
License: GNU General Public License v3.0
Project-URL: Bug Tracker, https://github.com/fbernhart/officeextractor/issues
Project-URL: Source Code, https://github.com/fbernhart/officeextractor
Keywords: office extractor media images audio video extract docx pptx xlsx libreoffice microsoft
Classifier: License :: OSI Approved :: GNU General Public License v3 (GPLv3)
Classifier: Programming Language :: Python :: 3
Classifier: Programming Language :: Python :: 3.9
Classifier: Programming Language :: Python :: 3.10
Classifier: Programming Language :: Python :: 3.11
Classifier: Programming Language :: Python :: 3.12
Classifier: Programming Language :: Python :: 3.13
Classifier: Operating System :: OS Independent
Classifier: Topic :: Office/Business
Classifier: Topic :: Office/Business :: Office Suites
Classifier: Topic :: Utilities
Requires-Python: >=3.9
License-File: LICENSE
